twitchyterm
