Metadata-Version: 1.1
Name: twitchy-term
Version: 1.0.1
Summary: A terminal tool for browsing/streaming on Twitch.tv.
Home-page: https://github.com/Andy-Au/twitchy-term
Author: Andy Au
Author-email: au.andy.ch@gmail.com
License: MIT
Keywords: twitch livestreamer command line interface terminal stream
Platform: UNKNOWN
Classifier: Intended Audience :: End Users/Desktop
Classifier: Environment :: Console :: Curses
Classifier: Operating System :: POSIX
Classifier: Natural Language :: English
Classifier: Programming Language :: Python :: 3 :: Only
Classifier: Programming Language :: Python :: 3.4
Classifier: Topic :: Multimedia :: Video
Classifier: Topic :: Multimedia :: Sound/Audio
Classifier: Topic :: Games/Entertainment
